{
  "generatedAt": "2026-02-20T13:58:41.411Z",
  "bitcoin": {
    "coinGeckoPrice": {
      "usd": 66805
    }
  },
  "pi": {
    "cmc": {
      "status": {
        "timestamp": "2026-02-20T13:58:41.257Z",
        "error_code": 0,
        "error_message": null,
        "elapsed": 23,
        "credit_count": 1,
        "notice": null
      },
      "data": {
        "PI": {
          "id": 35697,
          "name": "Pi",
          "symbol": "PI",
          "slug": "pi",
          "num_market_pairs": 69,
          "date_added": "2025-02-11T07:16:10.000Z",
          "tags": [
            "layer-1",
            "mobile-mining"
          ],
          "max_supply": 100000000000,
          "circulating_supply": 9062665847.451443,
          "total_supply": 100000000000,
          "is_active": 1,
          "infinite_supply": false,
          "minted_market_cap": 17274380887.39,
          "platform": null,
          "cmc_rank": 44,
          "is_fiat": 0,
          "self_reported_circulating_supply": 9062665847.45,
          "self_reported_market_cap": 1565519417.0395818,
          "tvl_ratio": null,
          "last_updated": "2026-02-20T13:57:00.000Z",
          "quote": {
            "USD": {
              "price": 0.17274380887386226,
              "volume_24h": 19363395.11641901,
              "volume_change_24h": -11.2422,
              "percent_change_1h": 0.1904738,
              "percent_change_24h": -4.93821193,
              "percent_change_7d": 17.81652952,
              "percent_change_30d": -3.1917534,
              "percent_change_60d": -16.55245202,
              "percent_change_90d": -27.71925602,
              "market_cap": 1565519417.039831,
              "market_cap_dominance": 0.0684,
              "fully_diluted_market_cap": 17274380887.39,
              "tvl": null,
              "last_updated": "2026-02-20T13:57:00.000Z"
            }
          }
        }
      }
    }
  },
  "news": {
    "articles": []
  }
}