{
  "generatedAt": "2026-01-31T19:40:43.795Z",
  "bitcoin": {
    "coinGeckoPrice": {
      "usd": 77228
    }
  },
  "pi": {
    "cmc": {
      "status": {
        "timestamp": "2026-01-31T19:40:43.535Z",
        "error_code": 0,
        "error_message": null,
        "elapsed": 55,
        "credit_count": 1,
        "notice": null
      },
      "data": {
        "PI": {
          "id": 35697,
          "name": "Pi",
          "symbol": "PI",
          "slug": "pi",
          "num_market_pairs": 69,
          "date_added": "2025-02-11T07:16:10.000Z",
          "tags": [
            "layer-1",
            "mobile-mining"
          ],
          "max_supply": 100000000000,
          "circulating_supply": 8645880921.843433,
          "total_supply": 100000000000,
          "is_active": 1,
          "infinite_supply": false,
          "minted_market_cap": 15388497537.52,
          "platform": null,
          "cmc_rank": 50,
          "is_fiat": 0,
          "self_reported_circulating_supply": 8645880921.84,
          "self_reported_market_cap": 1330471172.7542267,
          "tvl_ratio": null,
          "last_updated": "2026-01-31T19:38:00.000Z",
          "quote": {
            "USD": {
              "price": 0.15388497537519616,
              "volume_24h": 28043377.50030619,
              "volume_change_24h": 59.1716,
              "percent_change_1h": -1.01136545,
              "percent_change_24h": -8.48985033,
              "percent_change_7d": -15.27789013,
              "percent_change_30d": -24.63199789,
              "percent_change_60d": -34.66244019,
              "percent_change_90d": -38.18387614,
              "market_cap": 1330471172.754755,
              "market_cap_dominance": 0.0509,
              "fully_diluted_market_cap": 15388497537.52,
              "tvl": null,
              "last_updated": "2026-01-31T19:38:00.000Z"
            }
          }
        }
      }
    }
  },
  "news": {
    "articles": []
  }
}