{
  "generatedAt": "2026-03-14T21:57:10.378Z",
  "bitcoin": {
    "coinGeckoPrice": {
      "usd": 70793
    }
  },
  "pi": {
    "cmc": {
      "status": {
        "timestamp": "2026-03-14T21:57:09.970Z",
        "error_code": 0,
        "error_message": null,
        "elapsed": 1349,
        "credit_count": 1,
        "notice": null
      },
      "data": {
        "PI": {
          "id": 35697,
          "name": "Pi",
          "symbol": "PI",
          "slug": "pi",
          "num_market_pairs": 71,
          "date_added": "2025-02-11T07:16:10.000Z",
          "tags": [
            "layer-1",
            "mobile-mining"
          ],
          "max_supply": 100000000000,
          "circulating_supply": 9677953023.729967,
          "total_supply": 100000000000,
          "is_active": 1,
          "infinite_supply": false,
          "minted_market_cap": 19825753874.08,
          "platform": null,
          "cmc_rank": 39,
          "is_fiat": 0,
          "self_reported_circulating_supply": 9672916045.62,
          "self_reported_market_cap": 1917728527.6509645,
          "tvl_ratio": null,
          "last_updated": "2026-03-14T21:56:00.000Z",
          "quote": {
            "USD": {
              "price": 0.19825753874079496,
              "volume_24h": 89060941.98202129,
              "cex_volume_24h": 89060941.98202129,
              "dex_volume_24h": 0,
              "volume_change_24h": -48.5044,
              "percent_change_1h": -0.00297707,
              "percent_change_24h": -15.74751378,
              "percent_change_7d": -14.17074868,
              "percent_change_30d": 47.67231761,
              "percent_change_60d": -4.57863903,
              "percent_change_90d": -1.69468734,
              "market_cap": 1918727146.5337377,
              "market_cap_dominance": 0.0796,
              "fully_diluted_market_cap": 19825753874.08,
              "tvl": null,
              "last_updated": "2026-03-14T21:56:00.000Z"
            }
          }
        }
      }
    }
  },
  "news": {
    "articles": []
  }
}