{
  "generatedAt": "2026-03-22T11:20:35.656Z",
  "bitcoin": {
    "coinGeckoPrice": {
      "usd": 68624
    }
  },
  "pi": {
    "cmc": {
      "status": {
        "timestamp": "2026-03-22T11:20:35.401Z",
        "error_code": 0,
        "error_message": null,
        "elapsed": 16,
        "credit_count": 1,
        "notice": null
      },
      "data": {
        "PI": {
          "id": 35697,
          "name": "Pi",
          "symbol": "PI",
          "slug": "pi",
          "num_market_pairs": 71,
          "date_added": "2025-02-11T07:16:10.000Z",
          "tags": [
            "layer-1",
            "mobile-mining"
          ],
          "max_supply": 100000000000,
          "circulating_supply": 9812329500.444038,
          "total_supply": 100000000000,
          "is_active": 1,
          "infinite_supply": false,
          "minted_market_cap": 19064547290.77,
          "platform": null,
          "cmc_rank": 38,
          "is_fiat": 0,
          "self_reported_circulating_supply": 9812329500.44,
          "self_reported_market_cap": 1870676197.937806,
          "tvl_ratio": null,
          "last_updated": "2026-03-22T11:19:00.000Z",
          "quote": {
            "USD": {
              "price": 0.1906454729077251,
              "volume_24h": 27479711.02350638,
              "cex_volume_24h": 27479711.02350638,
              "dex_volume_24h": 0,
              "volume_change_24h": -28.1406,
              "percent_change_1h": -0.80823642,
              "percent_change_24h": -5.22904832,
              "percent_change_7d": -2.34934528,
              "percent_change_30d": 9.42672347,
              "percent_change_60d": 4.92067407,
              "percent_change_90d": -7.29541385,
              "market_cap": 1870676197.9385757,
              "market_cap_dominance": 0.0793,
              "fully_diluted_market_cap": 19064547290.77,
              "tvl": null,
              "last_updated": "2026-03-22T11:19:00.000Z"
            }
          }
        }
      }
    }
  },
  "news": {
    "articles": []
  }
}