{
  "generatedAt": "2025-12-09T14:19:19.606Z",
  "bitcoin": {
    "coinGeckoPrice": {
      "usd": 90321
    }
  },
  "pi": {
    "cmc": {
      "status": {
        "timestamp": "2025-12-09T14:19:19.335Z",
        "error_code": 0,
        "error_message": null,
        "elapsed": 18,
        "credit_count": 1,
        "notice": null
      },
      "data": {
        "PI": {
          "id": 35697,
          "name": "Pi",
          "symbol": "PI",
          "slug": "pi",
          "num_market_pairs": 67,
          "date_added": "2025-02-11T07:16:10.000Z",
          "tags": [
            "layer-1",
            "mobile-mining"
          ],
          "max_supply": 100000000000,
          "circulating_supply": 8346154501.006946,
          "total_supply": 100000000000,
          "is_active": 1,
          "infinite_supply": false,
          "minted_market_cap": 21694474933.52,
          "platform": null,
          "cmc_rank": 44,
          "is_fiat": 0,
          "self_reported_circulating_supply": 8346154501.01,
          "self_reported_market_cap": 1810654396.1341107,
          "tvl_ratio": null,
          "last_updated": "2025-12-09T14:15:00.000Z",
          "quote": {
            "USD": {
              "price": 0.21694474933515745,
              "volume_24h": 14722299.10244849,
              "volume_change_24h": -23.2784,
              "percent_change_1h": 0.44057777,
              "percent_change_24h": -0.79070792,
              "percent_change_7d": -6.70007991,
              "percent_change_30d": -2.93062383,
              "percent_change_60d": -8.619291,
              "percent_change_90d": -37.26217734,
              "market_cap": 1810654396.133448,
              "market_cap_dominance": 0.0588,
              "fully_diluted_market_cap": 21694474933.52,
              "tvl": null,
              "last_updated": "2025-12-09T14:15:00.000Z"
            }
          }
        }
      }
    }
  },
  "news": {
    "articles": []
  }
}