{
  "generatedAt": "2026-06-20T15:06:17.497Z",
  "bitcoin": {
    "coinGeckoPrice": {
      "usd": 63919
    }
  },
  "pi": {
    "cmc": {
      "data": {
        "PI": {
          "tags": [
            "layer-1",
            "mobile-mining"
          ],
          "id": 35697,
          "name": "Pi",
          "symbol": "PI",
          "slug": "pi",
          "is_active": 1,
          "infinite_supply": false,
          "is_fiat": 0,
          "circulating_supply": 10791897339.854424,
          "total_supply": 100000000000,
          "max_supply": 100000000000,
          "date_added": "2025-02-11T07:16:10.000Z",
          "num_market_pairs": 73,
          "cmc_rank": 45,
          "last_updated": "2026-06-20T15:05:00.000Z",
          "tvl_ratio": null,
          "platform": null,
          "self_reported_circulating_supply": 10791897339.85,
          "self_reported_market_cap": 1454531587.4627793,
          "minted_market_cap": 13477996886.53,
          "quote": {
            "USD": {
              "price": 0.13477996886532617,
              "volume_24h": 9828017.21534392,
              "volume_change_24h": 9.4811,
              "cex_volume_24h": 9828017.21534392,
              "dex_volume_24h": 0,
              "percent_change_1h": 0.1988487,
              "percent_change_24h": 0.29549553,
              "percent_change_7d": 4.50221937,
              "percent_change_30d": -10.57363865,
              "percent_change_60d": -19.74275263,
              "percent_change_90d": -28.85236701,
              "market_cap": 1454531587.4633756,
              "market_cap_dominance": 0.0663,
              "fully_diluted_market_cap": 13477996886.53,
              "tvl": null,
              "last_updated": "2026-06-20T15:05:03.000Z"
            }
          }
        }
      },
      "status": {
        "timestamp": "2026-06-20T15:06:17.456Z",
        "error_code": 0,
        "error_message": null,
        "elapsed": 4,
        "credit_count": 1,
        "notice": null
      }
    }
  },
  "news": {
    "articles": []
  }
}