{
  "generatedAt": "2025-12-25T21:38:44.622Z",
  "bitcoin": {
    "coinGeckoPrice": {
      "usd": 87900
    }
  },
  "pi": {
    "cmc": {
      "status": {
        "timestamp": "2025-12-25T21:38:44.292Z",
        "error_code": 0,
        "error_message": null,
        "elapsed": 25,
        "credit_count": 1,
        "notice": null
      },
      "data": {
        "PI": {
          "id": 35697,
          "name": "Pi",
          "symbol": "PI",
          "slug": "pi",
          "num_market_pairs": 67,
          "date_added": "2025-02-11T07:16:10.000Z",
          "tags": [
            "layer-1",
            "mobile-mining"
          ],
          "max_supply": 100000000000,
          "circulating_supply": 8371192248.925468,
          "total_supply": 100000000000,
          "is_active": 1,
          "infinite_supply": false,
          "minted_market_cap": 20629064967.54,
          "platform": null,
          "cmc_rank": 41,
          "is_fiat": 0,
          "self_reported_circulating_supply": 8371182118.63,
          "self_reported_market_cap": 1726896597.8028767,
          "tvl_ratio": null,
          "last_updated": "2025-12-25T21:37:00.000Z",
          "quote": {
            "USD": {
              "price": 0.20629064967535252,
              "volume_24h": 9681320.66862172,
              "volume_change_24h": -13.44,
              "percent_change_1h": 0.08595562,
              "percent_change_24h": 0.47145279,
              "percent_change_7d": 1.19658866,
              "percent_change_30d": -14.83356107,
              "percent_change_60d": -3.1897026,
              "percent_change_90d": -24.11232795,
              "market_cap": 1726898687.5881102,
              "market_cap_dominance": 0.0583,
              "fully_diluted_market_cap": 20629064967.54,
              "tvl": null,
              "last_updated": "2025-12-25T21:37:00.000Z"
            }
          }
        }
      }
    }
  },
  "news": {
    "articles": []
  }
}