{
  "generatedAt": "2026-05-07T19:58:15.916Z",
  "bitcoin": {
    "coinGeckoPrice": {
      "usd": 80080
    }
  },
  "pi": {
    "cmc": {
      "data": {
        "PI": {
          "tags": [
            "layer-1",
            "mobile-mining"
          ],
          "id": 35697,
          "name": "Pi",
          "symbol": "PI",
          "slug": "pi",
          "is_active": 1,
          "infinite_supply": false,
          "is_fiat": 0,
          "circulating_supply": 10442104479.150497,
          "total_supply": 100000000000,
          "max_supply": 100000000000,
          "date_added": "2025-02-11T07:16:10.000Z",
          "num_market_pairs": 73,
          "cmc_rank": 41,
          "last_updated": "2026-05-07T19:57:00.000Z",
          "tvl_ratio": null,
          "platform": null,
          "self_reported_circulating_supply": 10442104479.15,
          "self_reported_market_cap": 1826095823.252254,
          "minted_market_cap": 17487814136.49,
          "quote": {
            "USD": {
              "price": 0.17487814136493876,
              "volume_24h": 22692272.73360183,
              "volume_change_24h": -19.0461,
              "cex_volume_24h": 22692272.73360183,
              "dex_volume_24h": 0,
              "percent_change_1h": -0.29022995,
              "percent_change_24h": -3.61943706,
              "percent_change_7d": -0.4029113,
              "percent_change_30d": 4.78983238,
              "percent_change_60d": -16.23298177,
              "percent_change_90d": 15.73870985,
              "market_cap": 1826095823.2523408,
              "market_cap_dominance": 0.0686,
              "fully_diluted_market_cap": 17487814136.49,
              "tvl": null,
              "last_updated": "2026-05-07T19:57:04.000Z"
            }
          }
        }
      },
      "status": {
        "timestamp": "2026-05-07T19:58:15.784Z",
        "error_code": 0,
        "error_message": null,
        "elapsed": 4,
        "credit_count": 1,
        "notice": null
      }
    }
  },
  "news": {
    "articles": []
  }
}