{
  "generatedAt": "2025-12-31T03:11:39.058Z",
  "bitcoin": {
    "coinGeckoPrice": {
      "usd": 88668
    }
  },
  "pi": {
    "cmc": {
      "status": {
        "timestamp": "2025-12-31T03:11:38.765Z",
        "error_code": 0,
        "error_message": null,
        "elapsed": 43,
        "credit_count": 1,
        "notice": null
      },
      "data": {
        "PI": {
          "id": 35697,
          "name": "Pi",
          "symbol": "PI",
          "slug": "pi",
          "num_market_pairs": 67,
          "date_added": "2025-02-11T07:16:10.000Z",
          "tags": [
            "layer-1",
            "mobile-mining"
          ],
          "max_supply": 100000000000,
          "circulating_supply": 8376005319.4734125,
          "total_supply": 100000000000,
          "is_active": 1,
          "infinite_supply": false,
          "minted_market_cap": 20460982840.93,
          "platform": null,
          "cmc_rank": 44,
          "is_fiat": 0,
          "self_reported_circulating_supply": 8375946915.48,
          "self_reported_market_cap": 1713801061.1420016,
          "tvl_ratio": null,
          "last_updated": "2025-12-31T03:10:00.000Z",
          "quote": {
            "USD": {
              "price": 0.20460982840932784,
              "volume_24h": 8578248.26720392,
              "volume_change_24h": -16.8643,
              "percent_change_1h": 0.5778552,
              "percent_change_24h": 1.48079944,
              "percent_change_7d": 0.30300473,
              "percent_change_30d": -10.85941392,
              "percent_change_60d": -18.23090367,
              "percent_change_90d": -24.90263278,
              "market_cap": 1713813011.173072,
              "market_cap_dominance": 0.0572,
              "fully_diluted_market_cap": 20460982840.93,
              "tvl": null,
              "last_updated": "2025-12-31T03:10:00.000Z"
            }
          }
        }
      }
    }
  },
  "news": {
    "articles": []
  }
}