{
  "generatedAt": "2025-12-10T18:52:34.304Z",
  "bitcoin": {
    "coinGeckoPrice": {
      "usd": 92643
    }
  },
  "pi": {
    "cmc": {
      "status": {
        "timestamp": "2025-12-10T18:52:34.114Z",
        "error_code": 0,
        "error_message": null,
        "elapsed": 45,
        "credit_count": 1,
        "notice": null
      },
      "data": {
        "PI": {
          "id": 35697,
          "name": "Pi",
          "symbol": "PI",
          "slug": "pi",
          "num_market_pairs": 67,
          "date_added": "2025-02-11T07:16:10.000Z",
          "tags": [
            "layer-1",
            "mobile-mining"
          ],
          "max_supply": 100000000000,
          "circulating_supply": 8346154501.006946,
          "total_supply": 100000000000,
          "is_active": 1,
          "infinite_supply": false,
          "minted_market_cap": 21435021831.76,
          "platform": null,
          "cmc_rank": 45,
          "is_fiat": 0,
          "self_reported_circulating_supply": 8346154501.01,
          "self_reported_market_cap": 1789000039.4043245,
          "tvl_ratio": null,
          "last_updated": "2025-12-10T18:50:00.000Z",
          "quote": {
            "USD": {
              "price": 0.21435021831764925,
              "volume_24h": 15115469.95734189,
              "volume_change_24h": -12.1823,
              "percent_change_1h": 0.90413977,
              "percent_change_24h": -2.05607085,
              "percent_change_7d": -7.04055567,
              "percent_change_30d": -6.44567365,
              "percent_change_60d": 2.91245348,
              "percent_change_90d": -37.60533808,
              "market_cap": 1789000039.4036698,
              "market_cap_dominance": 0.0564,
              "fully_diluted_market_cap": 21435021831.76,
              "tvl": null,
              "last_updated": "2025-12-10T18:50:00.000Z"
            }
          }
        }
      }
    }
  },
  "news": {
    "articles": []
  }
}