{
  "generatedAt": "2026-03-04T11:29:06.151Z",
  "bitcoin": {
    "coinGeckoPrice": {
      "usd": 71252
    }
  },
  "pi": {
    "cmc": {
      "status": {
        "timestamp": "2026-03-04T11:29:05.735Z",
        "error_code": 0,
        "error_message": null,
        "elapsed": 415,
        "credit_count": 1,
        "notice": null
      },
      "data": {
        "PI": {
          "id": 35697,
          "name": "Pi",
          "symbol": "PI",
          "slug": "pi",
          "num_market_pairs": 69,
          "date_added": "2025-02-11T07:16:10.000Z",
          "tags": [
            "layer-1",
            "mobile-mining"
          ],
          "max_supply": 100000000000,
          "circulating_supply": 9562259320.068508,
          "total_supply": 100000000000,
          "is_active": 1,
          "infinite_supply": false,
          "minted_market_cap": 17377107884.1,
          "platform": null,
          "cmc_rank": 43,
          "is_fiat": 0,
          "self_reported_circulating_supply": 9562259320.07,
          "self_reported_market_cap": 1661644118.2063422,
          "tvl_ratio": null,
          "last_updated": "2026-03-04T11:28:00.000Z",
          "quote": {
            "USD": {
              "price": 0.17377107884103882,
              "volume_24h": 13237105.92737438,
              "cex_volume_24h": 13237105.92737438,
              "dex_volume_24h": 0,
              "volume_change_24h": 2.749,
              "percent_change_1h": -0.21457519,
              "percent_change_24h": 2.06778885,
              "percent_change_7d": 3.36070076,
              "percent_change_30d": 10.38855735,
              "percent_change_60d": -16.19947626,
              "percent_change_90d": -25.00235613,
              "market_cap": 1661644118.206083,
              "market_cap_dominance": 0.0688,
              "fully_diluted_market_cap": 17377107884.1,
              "tvl": null,
              "last_updated": "2026-03-04T11:28:00.000Z"
            }
          }
        }
      }
    }
  },
  "news": {
    "articles": []
  }
}