{
  "generatedAt": "2026-02-25T02:12:09.611Z",
  "bitcoin": {
    "coinGeckoPrice": {
      "usd": 66095
    }
  },
  "pi": {
    "cmc": {
      "status": {
        "timestamp": "2026-02-25T02:12:09.317Z",
        "error_code": 0,
        "error_message": null,
        "elapsed": 810,
        "credit_count": 1,
        "notice": null
      },
      "data": {
        "PI": {
          "id": 35697,
          "name": "Pi",
          "symbol": "PI",
          "slug": "pi",
          "num_market_pairs": 69,
          "date_added": "2025-02-11T07:16:10.000Z",
          "tags": [
            "layer-1",
            "mobile-mining"
          ],
          "max_supply": 100000000000,
          "circulating_supply": 9225492637.533705,
          "total_supply": 100000000000,
          "is_active": 1,
          "infinite_supply": false,
          "minted_market_cap": 16587555975.47,
          "platform": null,
          "cmc_rank": 46,
          "is_fiat": 0,
          "self_reported_circulating_supply": 9212524148.82,
          "self_reported_market_cap": 1528132599.9392884,
          "tvl_ratio": null,
          "last_updated": "2026-02-25T02:11:00.000Z",
          "quote": {
            "USD": {
              "price": 0.16587555975470866,
              "volume_24h": 13727996.56771841,
              "volume_change_24h": -6.6735,
              "percent_change_1h": 1.28183787,
              "percent_change_24h": 1.88521157,
              "percent_change_7d": -11.06541654,
              "percent_change_30d": -4.83659301,
              "percent_change_60d": -18.90315185,
              "percent_change_90d": -35.15103339,
              "market_cap": 1530283755.2638469,
              "market_cap_dominance": 0.0674,
              "fully_diluted_market_cap": 16587555975.47,
              "tvl": null,
              "last_updated": "2026-02-25T02:11:00.000Z"
            }
          }
        }
      }
    }
  },
  "news": {
    "articles": []
  }
}