{
  "generatedAt": "2025-11-28T06:26:48.038Z",
  "bitcoin": {
    "coinGeckoPrice": {
      "usd": 91321
    }
  },
  "pi": {
    "cmc": {
      "status": {
        "timestamp": "2025-11-28T06:26:47.773Z",
        "error_code": 0,
        "error_message": null,
        "elapsed": 41,
        "credit_count": 1,
        "notice": null
      },
      "data": {
        "PI": {
          "id": 35697,
          "name": "Pi",
          "symbol": "PI",
          "slug": "pi",
          "num_market_pairs": 66,
          "date_added": "2025-02-11T07:16:10.000Z",
          "tags": [
            "layer-1",
            "mobile-mining"
          ],
          "max_supply": 100000000000,
          "circulating_supply": 8334670429.679167,
          "total_supply": 100000000000,
          "is_active": 1,
          "infinite_supply": false,
          "minted_market_cap": 26099444438.88,
          "platform": null,
          "cmc_rank": 40,
          "is_fiat": 0,
          "self_reported_circulating_supply": 8334643697.28,
          "self_reported_market_cap": 2175295700.9499946,
          "tvl_ratio": null,
          "last_updated": "2025-11-28T06:25:00.000Z",
          "quote": {
            "USD": {
              "price": 0.26099444438877445,
              "volume_24h": 73168055.17778032,
              "volume_change_24h": 54.9406,
              "percent_change_1h": 0.36656558,
              "percent_change_24h": 3.35755984,
              "percent_change_7d": 9.53977723,
              "percent_change_30d": -1.51735036,
              "percent_change_60d": -1.76670469,
              "percent_change_90d": -28.48779619,
              "market_cap": 2175302677.957662,
              "market_cap_dominance": 0.07,
              "fully_diluted_market_cap": 26099444438.88,
              "tvl": null,
              "last_updated": "2025-11-28T06:25:00.000Z"
            }
          }
        }
      }
    }
  },
  "news": {
    "articles": []
  }
}