{
  "generatedAt": "2026-02-04T21:04:40.700Z",
  "bitcoin": {
    "coinGeckoPrice": {
      "usd": 73412
    }
  },
  "pi": {
    "cmc": {
      "status": {
        "timestamp": "2026-02-04T21:04:40.543Z",
        "error_code": 0,
        "error_message": null,
        "elapsed": 50,
        "credit_count": 1,
        "notice": null
      },
      "data": {
        "PI": {
          "id": 35697,
          "name": "Pi",
          "symbol": "PI",
          "slug": "pi",
          "num_market_pairs": 69,
          "date_added": "2025-02-11T07:16:10.000Z",
          "tags": [
            "layer-1",
            "mobile-mining"
          ],
          "max_supply": 100000000000,
          "circulating_supply": 8756366464.974415,
          "total_supply": 100000000000,
          "is_active": 1,
          "infinite_supply": false,
          "minted_market_cap": 15904175202.6,
          "platform": null,
          "cmc_rank": 50,
          "is_fiat": 0,
          "self_reported_circulating_supply": 8756366464.97,
          "self_reported_market_cap": 1392627863.9705138,
          "tvl_ratio": null,
          "last_updated": "2026-02-04T21:03:00.000Z",
          "quote": {
            "USD": {
              "price": 0.1590417520259969,
              "volume_24h": 13893821.61520484,
              "volume_change_24h": -10.6481,
              "percent_change_1h": -0.19613403,
              "percent_change_24h": -2.14659871,
              "percent_change_7d": -6.20524386,
              "percent_change_30d": -25.66991755,
              "percent_change_60d": -29.39373015,
              "percent_change_90d": -26.47182991,
              "market_cap": 1392627863.971216,
              "market_cap_dominance": 0.0558,
              "fully_diluted_market_cap": 15904175202.6,
              "tvl": null,
              "last_updated": "2026-02-04T21:03:00.000Z"
            }
          }
        }
      }
    }
  },
  "news": {
    "articles": []
  }
}