{
  "generatedAt": "2026-04-18T13:35:01.681Z",
  "bitcoin": {
    "coinGeckoPrice": {
      "usd": 76043
    }
  },
  "pi": {
    "cmc": {
      "status": {
        "timestamp": "2026-04-18T13:35:01.463Z",
        "error_code": 0,
        "error_message": null,
        "elapsed": 21,
        "credit_count": 1,
        "notice": null
      },
      "data": {
        "PI": {
          "id": 35697,
          "name": "Pi",
          "symbol": "PI",
          "slug": "pi",
          "num_market_pairs": 73,
          "date_added": "2025-02-11T07:16:10.000Z",
          "tags": [
            "layer-1",
            "mobile-mining"
          ],
          "max_supply": 100000000000,
          "circulating_supply": 10190254564.848742,
          "total_supply": 100000000000,
          "is_active": 1,
          "infinite_supply": false,
          "minted_market_cap": 17396483612.38,
          "platform": null,
          "cmc_rank": 43,
          "is_fiat": 0,
          "self_reported_circulating_supply": 10186067502.06,
          "self_reported_market_cap": 1772017563.7415757,
          "tvl_ratio": null,
          "last_updated": "2026-04-18T13:34:00.000Z",
          "quote": {
            "USD": {
              "price": 0.17396483612377478,
              "volume_24h": 31763045.6705872,
              "cex_volume_24h": 31763045.6705872,
              "dex_volume_24h": 0,
              "volume_change_24h": -0.8076,
              "percent_change_1h": -3.03251771,
              "percent_change_24h": -3.71254845,
              "percent_change_7d": 4.13503632,
              "percent_change_30d": -0.14300061,
              "percent_change_60d": -2.40729018,
              "percent_change_90d": -14.54802782,
              "market_cap": 1772745965.4334593,
              "market_cap_dominance": 0.069,
              "fully_diluted_market_cap": 17396483612.38,
              "tvl": null,
              "last_updated": "2026-04-18T13:34:00.000Z"
            }
          }
        }
      }
    }
  },
  "news": {
    "articles": []
  }
}