{
  "generatedAt": "2026-02-07T09:45:15.634Z",
  "bitcoin": {
    "coinGeckoPrice": {
      "usd": 68081
    }
  },
  "pi": {
    "cmc": {
      "status": {
        "timestamp": "2026-02-07T09:45:15.563Z",
        "error_code": 0,
        "error_message": null,
        "elapsed": 20,
        "credit_count": 1,
        "notice": null
      },
      "data": {
        "PI": {
          "id": 35697,
          "name": "Pi",
          "symbol": "PI",
          "slug": "pi",
          "num_market_pairs": 69,
          "date_added": "2025-02-11T07:16:10.000Z",
          "tags": [
            "layer-1",
            "mobile-mining"
          ],
          "max_supply": 100000000000,
          "circulating_supply": 8894310953.790905,
          "total_supply": 100000000000,
          "is_active": 1,
          "infinite_supply": false,
          "minted_market_cap": 14495888858.01,
          "platform": null,
          "cmc_rank": 50,
          "is_fiat": 0,
          "self_reported_circulating_supply": 8875217617.41,
          "self_reported_market_cap": 1286541681.726351,
          "tvl_ratio": null,
          "last_updated": "2026-02-07T09:44:00.000Z",
          "quote": {
            "USD": {
              "price": 0.14495888858010836,
              "volume_24h": 20648286.55775202,
              "volume_change_24h": -40.6078,
              "percent_change_1h": -0.26309087,
              "percent_change_24h": 0.77159146,
              "percent_change_7d": -14.13849464,
              "percent_change_30d": -30.14033592,
              "percent_change_60d": -33.44760613,
              "percent_change_90d": -34.78621351,
              "market_cap": 1289309430.547413,
              "market_cap_dominance": 0.0553,
              "fully_diluted_market_cap": 14495888858.01,
              "tvl": null,
              "last_updated": "2026-02-07T09:44:00.000Z"
            }
          }
        }
      }
    }
  },
  "news": {
    "articles": []
  }
}