{
  "generatedAt": "2025-12-12T05:54:37.158Z",
  "bitcoin": {
    "coinGeckoPrice": {
      "usd": 92420
    }
  },
  "pi": {
    "cmc": {
      "status": {
        "timestamp": "2025-12-12T05:54:37.072Z",
        "error_code": 0,
        "error_message": null,
        "elapsed": 20,
        "credit_count": 1,
        "notice": null
      },
      "data": {
        "PI": {
          "id": 35697,
          "name": "Pi",
          "symbol": "PI",
          "slug": "pi",
          "num_market_pairs": 67,
          "date_added": "2025-02-11T07:16:10.000Z",
          "tags": [
            "layer-1",
            "mobile-mining"
          ],
          "max_supply": 100000000000,
          "circulating_supply": 8355906354.660181,
          "total_supply": 100000000000,
          "is_active": 1,
          "infinite_supply": false,
          "minted_market_cap": 21028790309.37,
          "platform": null,
          "cmc_rank": 45,
          "is_fiat": 0,
          "self_reported_circulating_supply": 8355837451.91,
          "self_reported_market_cap": 1757131536.3543234,
          "tvl_ratio": null,
          "last_updated": "2025-12-12T05:52:00.000Z",
          "quote": {
            "USD": {
              "price": 0.2102879030937436,
              "volume_24h": 14935510.65094584,
              "volume_change_24h": -26.6287,
              "percent_change_1h": 0.45347425,
              "percent_change_24h": 1.02519603,
              "percent_change_7d": -8.18380217,
              "percent_change_30d": -6.7002015,
              "percent_change_60d": -1.57329074,
              "percent_change_90d": -43.42536218,
              "market_cap": 1757146025.7691765,
              "market_cap_dominance": 0.056,
              "fully_diluted_market_cap": 21028790309.37,
              "tvl": null,
              "last_updated": "2025-12-12T05:52:00.000Z"
            }
          }
        }
      }
    }
  },
  "news": {
    "articles": []
  }
}