{
  "generatedAt": "2025-12-13T17:14:37.006Z",
  "bitcoin": {
    "coinGeckoPrice": {
      "usd": 89997
    }
  },
  "pi": {
    "cmc": {
      "status": {
        "timestamp": "2025-12-13T17:14:36.722Z",
        "error_code": 0,
        "error_message": null,
        "elapsed": 24,
        "credit_count": 1,
        "notice": null
      },
      "data": {
        "PI": {
          "id": 35697,
          "name": "Pi",
          "symbol": "PI",
          "slug": "pi",
          "num_market_pairs": 67,
          "date_added": "2025-02-11T07:16:10.000Z",
          "tags": [
            "layer-1",
            "mobile-mining"
          ],
          "max_supply": 100000000000,
          "circulating_supply": 8358851453.983455,
          "total_supply": 100000000000,
          "is_active": 1,
          "infinite_supply": false,
          "minted_market_cap": 20614649350.33,
          "platform": null,
          "cmc_rank": 45,
          "is_fiat": 0,
          "self_reported_circulating_supply": 8358826972.66,
          "self_reported_market_cap": 1723142870.2148116,
          "tvl_ratio": null,
          "last_updated": "2025-12-13T17:14:00.000Z",
          "quote": {
            "USD": {
              "price": 0.2061464935033177,
              "volume_24h": 9345383.88393057,
              "volume_change_24h": -35.907,
              "percent_change_1h": -0.15676686,
              "percent_change_24h": -0.36922758,
              "percent_change_7d": -9.05859301,
              "percent_change_30d": -7.53988897,
              "percent_change_60d": -4.54657195,
              "percent_change_90d": -42.19000482,
              "market_cap": 1723147916.953798,
              "market_cap_dominance": 0.0562,
              "fully_diluted_market_cap": 20614649350.33,
              "tvl": null,
              "last_updated": "2025-12-13T17:14:00.000Z"
            }
          }
        }
      }
    }
  },
  "news": {
    "articles": []
  }
}