{
  "generatedAt": "2025-12-16T05:45:00.629Z",
  "bitcoin": {
    "coinGeckoPrice": {
      "usd": 86065
    }
  },
  "pi": {
    "cmc": {
      "status": {
        "timestamp": "2025-12-16T05:45:00.369Z",
        "error_code": 0,
        "error_message": null,
        "elapsed": 54,
        "credit_count": 1,
        "notice": null
      },
      "data": {
        "PI": {
          "id": 35697,
          "name": "Pi",
          "symbol": "PI",
          "slug": "pi",
          "num_market_pairs": 67,
          "date_added": "2025-02-11T07:16:10.000Z",
          "tags": [
            "layer-1",
            "mobile-mining"
          ],
          "max_supply": 100000000000,
          "circulating_supply": 8361523981.274091,
          "total_supply": 100000000000,
          "is_active": 1,
          "infinite_supply": false,
          "minted_market_cap": 19422584246.14,
          "platform": null,
          "cmc_rank": 45,
          "is_fiat": 0,
          "self_reported_circulating_supply": 8361523981.27,
          "self_reported_market_cap": 1624024039.5231376,
          "tvl_ratio": null,
          "last_updated": "2025-12-16T05:41:00.000Z",
          "quote": {
            "USD": {
              "price": 0.19422584246137278,
              "volume_24h": 19568805.95548478,
              "volume_change_24h": 38.5274,
              "percent_change_1h": 0.21242239,
              "percent_change_24h": -6.1058129,
              "percent_change_7d": -11.52174595,
              "percent_change_30d": -14.30016595,
              "percent_change_60d": -6.27567248,
              "percent_change_90d": -45.32461313,
              "market_cap": 1624024039.5239322,
              "market_cap_dominance": 0.0555,
              "fully_diluted_market_cap": 19422584246.14,
              "tvl": null,
              "last_updated": "2025-12-16T05:41:00.000Z"
            }
          }
        }
      }
    }
  },
  "news": {
    "articles": []
  }
}