{
  "generatedAt": "2025-12-12T07:42:28.078Z",
  "bitcoin": {
    "coinGeckoPrice": {
      "usd": 92323
    }
  },
  "pi": {
    "cmc": {
      "status": {
        "timestamp": "2025-12-12T07:42:27.781Z",
        "error_code": 0,
        "error_message": null,
        "elapsed": 23,
        "credit_count": 1,
        "notice": null
      },
      "data": {
        "PI": {
          "id": 35697,
          "name": "Pi",
          "symbol": "PI",
          "slug": "pi",
          "num_market_pairs": 67,
          "date_added": "2025-02-11T07:16:10.000Z",
          "tags": [
            "layer-1",
            "mobile-mining"
          ],
          "max_supply": 100000000000,
          "circulating_supply": 8356035198.392203,
          "total_supply": 100000000000,
          "is_active": 1,
          "infinite_supply": false,
          "minted_market_cap": 20871364026.95,
          "platform": null,
          "cmc_rank": 45,
          "is_fiat": 0,
          "self_reported_circulating_supply": 8355901435.47,
          "self_reported_market_cap": 1743990606.3299637,
          "tvl_ratio": null,
          "last_updated": "2025-12-12T07:40:00.000Z",
          "quote": {
            "USD": {
              "price": 0.20871364026948558,
              "volume_24h": 14742136.62719332,
              "volume_change_24h": -28.5911,
              "percent_change_1h": -0.45373803,
              "percent_change_24h": -0.04491049,
              "percent_change_7d": -9.1153334,
              "percent_change_30d": -7.94821608,
              "percent_change_60d": -4.62641476,
              "percent_change_90d": -43.59381234,
              "market_cap": 1744018524.47639,
              "market_cap_dominance": 0.0555,
              "fully_diluted_market_cap": 20871364026.95,
              "tvl": null,
              "last_updated": "2025-12-12T07:40:00.000Z"
            }
          }
        }
      }
    }
  },
  "news": {
    "articles": []
  }
}