{
  "generatedAt": "2026-06-10T00:09:15.528Z",
  "bitcoin": {
    "coinGeckoPrice": {
      "usd": 61834
    }
  },
  "pi": {
    "cmc": {
      "data": {
        "PI": {
          "tags": [
            "layer-1",
            "mobile-mining"
          ],
          "id": 35697,
          "name": "Pi",
          "symbol": "PI",
          "slug": "pi",
          "is_active": 1,
          "infinite_supply": false,
          "is_fiat": 0,
          "circulating_supply": 10691997303.676582,
          "total_supply": 100000000000,
          "max_supply": 100000000000,
          "date_added": "2025-02-11T07:16:10.000Z",
          "num_market_pairs": 73,
          "cmc_rank": 47,
          "last_updated": "2026-06-10T00:07:00.000Z",
          "tvl_ratio": null,
          "platform": null,
          "self_reported_circulating_supply": 10691997303.68,
          "self_reported_market_cap": 1364976290.0488937,
          "minted_market_cap": 12766335898.52,
          "quote": {
            "USD": {
              "price": 0.12766335898523773,
              "volume_24h": 7934618.31582728,
              "volume_change_24h": 14.9262,
              "cex_volume_24h": 7934618.31582728,
              "dex_volume_24h": 0,
              "percent_change_1h": 0.34389147,
              "percent_change_24h": -1.39584112,
              "percent_change_7d": -7.74681863,
              "percent_change_30d": -27.00667639,
              "percent_change_60d": -24.26630757,
              "percent_change_90d": -43.61612702,
              "market_cap": 1364976290.0484574,
              "market_cap_dominance": 0.064,
              "fully_diluted_market_cap": 12766335898.52,
              "tvl": null,
              "last_updated": "2026-06-10T00:08:04.000Z"
            }
          }
        }
      },
      "status": {
        "timestamp": "2026-06-10T00:09:15.303Z",
        "error_code": 0,
        "error_message": null,
        "elapsed": 4,
        "credit_count": 1,
        "notice": null
      }
    }
  },
  "news": {
    "articles": []
  }
}