{
  "generatedAt": "2026-02-01T22:51:59.744Z",
  "bitcoin": {
    "coinGeckoPrice": {
      "usd": 77280
    }
  },
  "pi": {
    "cmc": {
      "status": {
        "timestamp": "2026-02-01T22:51:59.386Z",
        "error_code": 0,
        "error_message": null,
        "elapsed": 48,
        "credit_count": 1,
        "notice": null
      },
      "data": {
        "PI": {
          "id": 35697,
          "name": "Pi",
          "symbol": "PI",
          "slug": "pi",
          "num_market_pairs": 69,
          "date_added": "2025-02-11T07:16:10.000Z",
          "tags": [
            "layer-1",
            "mobile-mining"
          ],
          "max_supply": 100000000000,
          "circulating_supply": 8646259735.721767,
          "total_supply": 100000000000,
          "is_active": 1,
          "infinite_supply": false,
          "minted_market_cap": 15855673828.74,
          "platform": null,
          "cmc_rank": 48,
          "is_fiat": 0,
          "self_reported_circulating_supply": 8646256382.38,
          "self_reported_market_cap": 1370922210.3867905,
          "tvl_ratio": null,
          "last_updated": "2026-02-01T22:51:00.000Z",
          "quote": {
            "USD": {
              "price": 0.15855673828740036,
              "volume_24h": 16353789.38095935,
              "volume_change_24h": -44.1693,
              "percent_change_1h": 0.02458164,
              "percent_change_24h": 0.42399542,
              "percent_change_7d": -7.59868921,
              "percent_change_30d": -24.44834208,
              "percent_change_60d": -31.56719773,
              "percent_change_90d": -30.27898674,
              "market_cap": 1370922742.0817237,
              "market_cap_dominance": 0.0525,
              "fully_diluted_market_cap": 15855673828.74,
              "tvl": null,
              "last_updated": "2026-02-01T22:51:00.000Z"
            }
          }
        }
      }
    }
  },
  "news": {
    "articles": []
  }
}