{
  "generatedAt": "2025-12-22T04:25:59.259Z",
  "bitcoin": {
    "coinGeckoPrice": {
      "usd": 88954
    }
  },
  "pi": {
    "cmc": {
      "status": {
        "timestamp": "2025-12-22T04:25:59.071Z",
        "error_code": 0,
        "error_message": null,
        "elapsed": 56,
        "credit_count": 1,
        "notice": null
      },
      "data": {
        "PI": {
          "id": 35697,
          "name": "Pi",
          "symbol": "PI",
          "slug": "pi",
          "num_market_pairs": 67,
          "date_added": "2025-02-11T07:16:10.000Z",
          "tags": [
            "layer-1",
            "mobile-mining"
          ],
          "max_supply": 100000000000,
          "circulating_supply": 8367620378.676471,
          "total_supply": 100000000000,
          "is_active": 1,
          "infinite_supply": false,
          "minted_market_cap": 20550459547.78,
          "platform": null,
          "cmc_rank": 43,
          "is_fiat": 0,
          "self_reported_circulating_supply": 8367594860.35,
          "self_reported_market_cap": 1719579196.898191,
          "tvl_ratio": null,
          "last_updated": "2025-12-22T04:24:00.000Z",
          "quote": {
            "USD": {
              "price": 0.20550459547778158,
              "volume_24h": 11571827.90026484,
              "volume_change_24h": -6.3198,
              "percent_change_1h": -0.15275766,
              "percent_change_24h": -0.33955284,
              "percent_change_7d": 0.22739784,
              "percent_change_30d": -13.18346777,
              "percent_change_60d": 2.54822166,
              "percent_change_90d": -24.12084105,
              "market_cap": 1719584441.0315497,
              "market_cap_dominance": 0.0572,
              "fully_diluted_market_cap": 20550459547.78,
              "tvl": null,
              "last_updated": "2025-12-22T04:24:00.000Z"
            }
          }
        }
      }
    }
  },
  "news": {
    "articles": []
  }
}